sandia/__init__.py
sandia/galen.py
sandia/galen/GalenView.ipynb
sandia/galen/__init__.py
sandia/galen/dataprep.py
sandia/galen/viewer.py
galen_view-0.0.2.dist-info/LICENSE.txt
galen_view-0.0.2.dist-info/METADATA
galen_view-0.0.2.dist-info/WHEEL
galen_view-0.0.2.dist-info/top_level.txt
galen_view-0.0.2.dist-info/RECORD
