Metadata-Version: 2.1
Name: galen-view
Version: 0.0.2
Summary: A utility for viewing and exploring the cord-19 dataset
Home-page: https://github.com/sandialabs/galen-view
Author: Travis Bauer
Author-email: tlbauer@sandia.gov
License: MIT
Platform: UNKNOWN
Classifier: Programming Language :: Python :: 3
Classifier: License :: OSI Approved :: MIT License
Classifier: Operating System :: OS Independent
Requires-Python: >=3.6
Requires-Dist: holoviews[recommended]
Requires-Dist: whoosh
Requires-Dist: cord-19-tools
Requires-Dist: scikit-learn
Requires-Dist: requests
